{"type": "Feature", "id": 12524358, "properties": {"woe:id": 12524358, "woe:parent_id": 102271, "woe:name": "Iriona Airport", "woe:placetype": 14, "woe:placetype_name": "Airport", "woe:lang": "ENG", "iso:country": "HN", "meta:provider": ["geoplanet:7.3.1", "geoplanet:7.3.2", "geoplanet:7.4.0", "geoplanet:7.4.1", "geoplanet:7.5.1", "geoplanet:7.5.2", "geoplanet:7.6.0", "geoplanet:7.8.1", "geoplanet:7.9.0", "geoplanet:7.10.0", "geoplanet:8.0.0", "woeplanet:8.0.0"], "meta:indexed": "2020-08-20T20:25:59.265716", "woe:alias_ENG_V": ["IRN Airport", "IRN"], "meta:updated": "2020-08-22T01:58:52.517315", "woe:hierarchy": {"continent": 24865672, "country": 23424841, "town": 0, "planet": 1, "county": 26813673, "suburb": 0, "state": 2345625, "region": 0, "localadmin": 0}, "woe:timezone_id": 28350799, "woe:hash": "d4g6m54xypyu", "woe:centroid": [-85.206261, 15.88211], "geom:latitude": 15.88211, "geom:longitude": -85.206261, "geom:hash": "d4g6m54xypyu", "woe:latitude": 15.88211, "geom:centroid": [-85.206261, 15.88211], "woe:longitude": -85.206261, "woe:repo": "woeplanet-airport-hn"}, "geometry": {"coordinates": [-85.206261, 15.88211], "type": "Point"}}