{"type": "Feature", "id": 12513362, "properties": {"woe:id": 12513362, "woe:parent_id": 107195, "woe:name": "Roatan Island Airport", "woe:placetype": 14, "woe:placetype_name": "Airport", "woe:lang": "ENG", "iso:country": "HN", "meta:provider": ["geoplanet:7.3.1", "geoplanet:7.3.2", "geoplanet:7.4.0", "geoplanet:7.4.1", "geoplanet:7.5.1", "geoplanet:7.5.2", "geoplanet:7.6.0", "geoplanet:7.8.1", "geoplanet:7.9.0", "geoplanet:7.10.0", "geoplanet:8.0.0", "woeplanet:8.0.0"], "meta:indexed": "2020-08-20T20:25:59.254824", "woe:alias_ENG_V": ["RTB Airport", "RTB", "Roatan Island"], "meta:updated": "2020-08-22T01:58:52.513005", "woe:hierarchy": {"continent": 24865672, "country": 23424841, "town": 0, "planet": 1, "county": 26813756, "suburb": 0, "state": 2345633, "region": 0, "localadmin": 0}, "woe:timezone_id": 28350799, "woe:hash": "d4fkygtp75qq", "woe:centroid": [-86.532303, 16.3242], "geom:latitude": 16.3242, "geom:longitude": -86.532303, "geom:hash": "d4fkygtp75qq", "woe:latitude": 16.3242, "geom:centroid": [-86.532303, 16.3242], "woe:longitude": -86.532303, "woe:repo": "woeplanet-airport-hn"}, "geometry": {"coordinates": [-86.532303, 16.3242], "type": "Point"}}