{"type": "Feature", "id": 12513360, "geometry": {"type": "Point", "coordinates": [-87.898903, 15.4431]}, "properties": {"woe:id": 12513360, "woe:parent_id": 103182, "woe:name": "Las Limas Airport", "woe:placetype": 14, "woe:placetype_name": "Airport", "woe:lang": "ENG", "iso:country": "HN", "meta:provider": ["geoplanet:7.3.1", "geoplanet:7.3.2", "geoplanet:7.4.0", "geoplanet:7.4.1", "geoplanet:7.5.1", "geoplanet:7.5.2", "geoplanet:7.6.0", "geoplanet:7.8.1", "geoplanet:7.9.0", "geoplanet:7.10.0", "geoplanet:8.0.0", "woeplanet:8.0.0"], "meta:indexed": "2020-08-20T20:25:59.253146", "woe:alias_ENG_V": ["LLH Airport", "LLH"], "meta:updated": "2020-10-14T11:44:20.671700", "woe:hierarchy": {"continent": 24865672, "country": 23424841, "town": 0, "planet": 1, "county": 26813690, "suburb": 0, "state": 2345628, "region": 0, "localadmin": 0}, "woe:timezone_id": 28350799, "woe:hash": "d49rzg3fx47r", "woe:centroid": [-87.898903, 15.4431], "geom:latitude": 15.4431, "geom:longitude": -87.898903, "geom:hash": "d49rzg3fx47r", "woe:latitude": 15.4431, "geom:centroid": [-87.898903, 15.4431], "woe:longitude": -87.898903, "woe:repo": "woeplanet-airport-hn", "geom:area": 0.0, "woe:scale": 19}}